Metadata-Version: 1.0
Name: sofc
Version: 0.1.6
Summary: stackoverflow client for quick search
Home-page: https://cyy0523xc.github.io/
Author: Alex Cai
Author-email: cyy0523xc@gmail.com
License: MIT License
Keywords: stackoverflow
Platform: any
